bootstrap3_datetime/__init__.py
bootstrap3_datetime/widgets.py
bootstrap3_datetime/static/bootstrap3_datetime/css/bootstrap-datetimepicker.css
bootstrap3_datetime/static/bootstrap3_datetime/css/bootstrap-datetimepicker.min.css
bootstrap3_datetime/static/bootstrap3_datetime/js/bootstrap-datetimepicker.js
bootstrap3_datetime/static/bootstrap3_datetime/js/bootstrap-datetimepicker.min.js
bootstrap3_datetime/static/bootstrap3_datetime/js/moment.min.js
bootstrap3_datetime/static/bootstrap3_datetime/js/locales/bootstrap-datetimepicker.ar-ma.js
bootstrap3_datetime/static/bootstrap3_datetime/js/locales/bootstrap-datetimepicker.ar.js
bootstrap3_datetime/static/bootstrap3_datetime/js/locales/bootstrap-datetimepicker.bg.js
bootstrap3_datetime/static/bootstrap3_datetime/js/locales/bootstrap-datetimepicker.br.js
bootstrap3_datetime/static/bootstrap3_datetime/js/locales/bootstrap-datetimepicker.bs.js
bootstrap3_datetime/static/bootstrap3_datetime/js/locales/bootstrap-datetimepicker.by.js
bootstrap3_datetime/static/bootstrap3_datetime/js/locales/bootstrap-datetimepicker.ca.js
bootstrap3_datetime/static/bootstrap3_datetime/js/locales/bootstrap-datetimepicker.cs.js
bootstrap3_datetime/static/bootstrap3_datetime/js/locales/bootstrap-datetimepicker.cv.js
bootstrap3_datetime/static/bootstrap3_datetime/js/locales/bootstrap-datetimepicker.da.js
bootstrap3_datetime/static/bootstrap3_datetime/js/locales/bootstrap-datetimepicker.de.js
bootstrap3_datetime/static/bootstrap3_datetime/js/locales/bootstrap-datetimepicker.el.js
bootstrap3_datetime/static/bootstrap3_datetime/js/locales/bootstrap-datetimepicker.en-au.js
bootstrap3_datetime/static/bootstrap3_datetime/js/locales/bootstrap-datetimepicker.en-ca.js
bootstrap3_datetime/static/bootstrap3_datetime/js/locales/bootstrap-datetimepicker.en-gb.js
bootstrap3_datetime/static/bootstrap3_datetime/js/locales/bootstrap-datetimepicker.eo.js
bootstrap3_datetime/static/bootstrap3_datetime/js/locales/bootstrap-datetimepicker.es.js
dpac_datetimepicker-3.1.dist-info/DESCRIPTION.rst
dpac_datetimepicker-3.1.dist-info/METADATA
dpac_datetimepicker-3.1.dist-info/RECORD
dpac_datetimepicker-3.1.dist-info/WHEEL
dpac_datetimepicker-3.1.dist-info/metadata.json
dpac_datetimepicker-3.1.dist-info/top_level.txt
