Metadata-Version: 2.0
Name: dpac-datetimepicker
Version: 3.1
Summary: Bootstrap3 compatible datetimepicker for Django2/dPAC project.
Home-page: https://github.com/david-pacheco/django-bootstrap3-datetimepicker.git
Author: David Pacheco
Author-email: davidpch@gmail.com
License: Apache License 2.0
Platform: UNKNOWN
Classifier: Intended Audience :: Developers
Classifier: License :: OSI Approved :: Apache Software License
Classifier: Programming Language :: Python
Classifier: Programming Language :: Python :: 2
Classifier: Programming Language :: Python :: 3
Classifier: Operating System :: OS Independent
Classifier: Topic :: Software Development :: Libraries
Classifier: Topic :: Utilities
Classifier: Environment :: Web Environment
Classifier: Framework :: Django
